{
  "unversionedId": "story",
  "id": "story",
  "isDocsHomePage": false,
  "title": "Story",
  "description": "",
  "source": "@site/docs/story.md",
  "sourceDirName": ".",
  "slug": "/story",
  "permalink": "/docs/story",
  "editUrl": "https://github.com/target-software/game-website/docs/story.md",
  "tags": [],
  "version": "current",
  "sidebarPosition": 2,
  "frontMatter": {
    "sidebar_position": 2
  },
  "sidebar": "tutorialSidebar",
  "previous": {
    "title": "Description",
    "permalink": "/docs/description"
  },
  "next": {
    "title": "Headquarters",
    "permalink": "/docs/gameplay/headquarters"
  }
}